windows_tools.server-0.1.1-py3.8-nspkg.pth
windows_tools/server/__init__.py
windows_tools.server-0.1.1.dist-info/LICENSE
windows_tools.server-0.1.1.dist-info/METADATA
windows_tools.server-0.1.1.dist-info/WHEEL
windows_tools.server-0.1.1.dist-info/namespace_packages.txt
windows_tools.server-0.1.1.dist-info/top_level.txt
windows_tools.server-0.1.1.dist-info/RECORD
