Metadata-Version: 2.1
Name: windows-tools.server
Version: 0.1.1
Summary: Windows server identification functions
Home-page: https://github.com/netinvent/windows_tools
Author: NetInvent - Orsiris de Jong
Author-email: contact@netinvent.fr
License: UNKNOWN
Keywords: wmi,virtualization,file,acl,ntfs,refs,antivirus,security,firewall,office
Platform: UNKNOWN
Classifier: Development Status :: 5 - Production/Stable
Classifier: Intended Audience :: Developers
Classifier: Topic :: Software Development
Classifier: Topic :: System
Classifier: Topic :: System :: Operating System
Classifier: Topic :: System :: Shells
Classifier: Programming Language :: Python
Classifier: Programming Language :: Python :: 3
Classifier: Programming Language :: Python :: Implementation :: CPython
Classifier: Programming Language :: Python :: Implementation :: PyPy
Classifier: Operating System :: Microsoft
Classifier: Operating System :: Microsoft :: Windows
Classifier: License :: OSI Approved :: BSD License
Requires-Python: >=3.5
